flask_odoowebservice/__init__.py
flask_odoowebservice/database.py
flask_odoowebservice/odooResources.py
flask_odoowebservice/webService.py
flask_odoowebservice-1.1.dist-info/METADATA
flask_odoowebservice-1.1.dist-info/RECORD
flask_odoowebservice-1.1.dist-info/WHEEL
flask_odoowebservice-1.1.dist-info/top_level.txt
